xmippBase/__init__.py
xmippBase/protocols/__init__.py
xmippBase/protocols/flexalign.py
xmippBase/protocols/morphology.py
scipion_em_xmippBase-24.6.0.0.dist-info/LICENSE
scipion_em_xmippBase-24.6.0.0.dist-info/METADATA
scipion_em_xmippBase-24.6.0.0.dist-info/WHEEL
scipion_em_xmippBase-24.6.0.0.dist-info/top_level.txt
scipion_em_xmippBase-24.6.0.0.dist-info/RECORD
