Metadata-Version: 2.1
Name: scipion-em-xmippBase
Version: 24.6.0.0
Summary: Scipion pseudoplugin to deal with the shared xmipp protocols.
Home-page: https://github.com/I2PC/scipion-em-xmippBase
Author: I2PC
Author-email: scipion@cnb.csic.es
License: UNKNOWN
Keywords: scipion cryoem imageprocessing Xmipp scipion-3.0
Platform: UNKNOWN
Requires-Dist: scipion-pyworkflow >=3.0
Requires-Dist: scipion-em
